django_select2/__init__.py
django_select2/db_client.py
django_select2/fields.py
django_select2/media.py
django_select2/memcache_client.py
django_select2/memcache_wrapped_db_client.py
django_select2/models.py
django_select2/urls.py
django_select2/util.py
django_select2/views.py
django_select2/widgets.py
django_select2/static/django_select2/css/all-bootstrapped.min.css
django_select2/static/django_select2/css/all.min.css
django_select2/static/django_select2/css/extra.css
django_select2/static/django_select2/css/select2-bootstrap.css
django_select2/static/django_select2/css/select2-bootstrap.min.css
django_select2/static/django_select2/css/select2-bootstrapped.min.css
django_select2/static/django_select2/css/select2-spinner.gif
django_select2/static/django_select2/css/select2.css
django_select2/static/django_select2/css/select2.min.css
django_select2/static/django_select2/css/select2.png
django_select2/static/django_select2/css/select2x2.png
django_select2/static/django_select2/js/heavy_data.js
django_select2/static/django_select2/js/heavy_data.min.js
django_select2/static/django_select2/js/select2.js
django_select2/static/django_select2/js/select2.min.js
django_select2/templatetags/__init__.py
django_select2/templatetags/django_select2_tags.py
tests/__init__.py
tests/conftest.py
tests/test_fields.py
tests/test_widgets.py
tests/testapp/__init__.py
tests/testapp/models.py
tests/testapp/settings.py
tests/testapp/urls.py
tests/testapp/views.py
tests/testapp/forms/__init__.py
tests/testapp/forms/fields.py
mysociety_Django_Select2-4.3.2.2.dist-info/LICENSE.txt
mysociety_Django_Select2-4.3.2.2.dist-info/METADATA
mysociety_Django_Select2-4.3.2.2.dist-info/WHEEL
mysociety_Django_Select2-4.3.2.2.dist-info/top_level.txt
mysociety_Django_Select2-4.3.2.2.dist-info/RECORD
