Metadata-Version: 2.1
Name: mysociety-Django-Select2
Version: 4.3.2.2
Summary: Select2 option fields for Django
Home-page: https://github.com/mysociety/django-select2
Author: Matthew Somerville
Author-email: matthew@mysociety.org
License: LICENSE.txt
Platform: UNKNOWN
Classifier: Development Status :: 5 - Production/Stable
Classifier: Environment :: Web Environment
Classifier: Intended Audience :: Developers
Classifier: License :: OSI Approved :: Apache Software License
Classifier: Operating System :: OS Independent
Classifier: Programming Language :: Python
Classifier: Framework :: Django
